kubernetes/__init__.py
kubernetes/api/__init__.py
kubernetes/api/admissionregistration_api.py
kubernetes/api/admissionregistration_v1_api.py
kubernetes/api/admissionregistration_v1alpha1_api.py
kubernetes/api/admissionregistration_v1beta1_api.py
kubernetes/api/apiextensions_api.py
kubernetes/api/apiextensions_v1_api.py
kubernetes/api/apiregistration_api.py
kubernetes/api/apiregistration_v1_api.py
kubernetes/api/apis_api.py
kubernetes/api/apps_api.py
kubernetes/api/apps_v1_api.py
kubernetes/api/authentication_api.py
kubernetes/api/authentication_v1_api.py
kubernetes/api/authorization_api.py
kubernetes/api/authorization_v1_api.py
kubernetes/api/autoscaling_api.py
kubernetes/api/autoscaling_v1_api.py
kubernetes/api/autoscaling_v2_api.py
kubernetes/api/batch_api.py
kubernetes/api/batch_v1_api.py
kubernetes/api/certificates_api.py
kubernetes/api/certificates_v1_api.py
kubernetes/api/certificates_v1alpha1_api.py
kubernetes/api/certificates_v1beta1_api.py
kubernetes/api/coordination_api.py
kubernetes/api/coordination_v1_api.py
kubernetes/api/coordination_v1alpha2_api.py
kubernetes/api/coordination_v1beta1_api.py
kubernetes/api/core_api.py
kubernetes/api/core_v1_api.py
kubernetes/api/discovery_api.py
kubernetes/api/discovery_v1_api.py
kubernetes/api/events_api.py
kubernetes/api/events_v1_api.py
kubernetes/api/flowcontrol_apiserver_api.py
kubernetes/api/flowcontrol_apiserver_v1_api.py
kubernetes/api/internal_apiserver_api.py
kubernetes/api/internal_apiserver_v1alpha1_api.py
kubernetes/api/logs_api.py
kubernetes/api/networking_api.py
kubernetes/api/networking_v1_api.py
kubernetes/api/networking_v1beta1_api.py
kubernetes/api/node_api.py
kubernetes/api/node_v1_api.py
kubernetes/api/openid_api.py
kubernetes/api/policy_api.py
kubernetes/api/policy_v1_api.py
kubernetes/api/rbac_authorization_api.py
kubernetes/api/rbac_authorization_v1_api.py
kubernetes/api/resource_api.py
kubernetes/api/resource_v1alpha3_api.py
kubernetes/api/resource_v1beta1_api.py
kubernetes_client_urllib3_pydantic-33.6.0.dist-info/METADATA
kubernetes_client_urllib3_pydantic-33.6.0.dist-info/WHEEL
kubernetes_client_urllib3_pydantic-33.6.0.dist-info/RECORD
