Metadata-Version: 2.4
Name: kubernetes_client_urllib3_pydantic
Version: 33.6.0
Summary: Synchronous Kubernetes client with Pydantic support
License-Expression: MIT
Keywords: OpenAPI,OpenAPI-Generator,Kubernetes
Author: Partho Bhowmick
Author-email: partho.bhowmick@icloud.com
Requires-Python: >=3.13,<4.0
Classifier: Programming Language :: Python :: 3
Classifier: Programming Language :: Python :: 3.13
Classifier: Programming Language :: Python :: 3.14
Requires-Dist: kubernetes-validate (>=1.34.0,<2.0.0)
Requires-Dist: lazy-imports (>=1.0.1)
Requires-Dist: oauthlib (>=3.3.1,<4.0.0)
Requires-Dist: pydantic (>=2,<3)
Requires-Dist: python-dateutil (>=2.8.2)
Requires-Dist: pyyaml (>=6.0.0,<7.0.0)
Requires-Dist: requests-oauthlib (>=2.0.0,<3.0.0)
Requires-Dist: typing-extensions (>=4.7.1)
Requires-Dist: urllib3 (>=1.25.3,<3.0.0)
